MANIFEST.in
setup.py
gcmaverager/__init__.py
gcmaverager/gcmaverager.py
gcmaverager.egg-info/PKG-INFO
gcmaverager.egg-info/SOURCES.txt
gcmaverager.egg-info/dependency_links.txt
gcmaverager.egg-info/not-zip-safe
gcmaverager.egg-info/requires.txt
gcmaverager.egg-info/top_level.txt