Metadata-Version: 1.1
Name: gcmaverager
Version: 0.14
Summary: A lightweight parallel post process package for GCM output.
Home-page: https://github.com/Yefee/gcmaverager
Author: Chengfei He
Author-email: che43@wisc.edu
License: MIT
Keywords: climate modeling modelling model gcm
Platform: UNKNOWN
Classifier: Development Status :: 3 - Alpha
Classifier: License :: OSI Approved :: MIT License
Classifier: Programming Language :: Python :: 2.7
Classifier: Programming Language :: Python :: 3.4
Classifier: Programming Language :: Python :: 3.5
Classifier: Programming Language :: Python :: 3.6
